yadageschemas/__init__.py
yadageschemas/utils.py
yadageschemas/validatecli.py
yadageschemas/validator.py
yadageschemas/dialects/__init__.py
yadageschemas/dialects/raw_with_defaults.py
yadageschemas/packtivity/packtivity-schema.json
yadageschemas/packtivity/environment/docker-enc-schema.json
yadageschemas/packtivity/environment/localproc-schema.json
yadageschemas/packtivity/environment/manual-instructions-env-schema.json
yadageschemas/packtivity/environment/noop-env-schema.json
yadageschemas/packtivity/process/manual-instructions-proc-schema.json
yadageschemas/packtivity/process/scriptproc-schema.json
yadageschemas/packtivity/process/stringinterp-schema.json
yadageschemas/packtivity/publisher/constant-pub-schema.json
yadageschemas/packtivity/publisher/fromglob-pub-schema.json
yadageschemas/packtivity/publisher/frompar-pub-schema.json
yadageschemas/packtivity/publisher/fromparjq-pub-schema.json
yadageschemas/packtivity/publisher/fromyaml-pub-schema.json
yadageschemas/packtivity/publisher/interpolated-pub-schema.json
yadageschemas/packtivity/publisher/manual-instructions-pub-schema.json
yadageschemas/yadage/stage-schema.json
yadageschemas/yadage/workflow-schema.json
yadageschemas/yadage/predicates/exprfulfilled-schema.json
yadageschemas/yadage/predicates/jsonpathready-schema.json
yadageschemas/yadage/scheduler/cases.json
yadageschemas/yadage/scheduler/jq-stage-schema.json
yadageschemas/yadage/scheduler/multistep-stage-schema.json
yadageschemas/yadage/scheduler/parameterselection.json
yadageschemas/yadage/scheduler/singlestep-stage-schema.json
yadageschemas/yadage/scheduler/value_registration.json
yadage_schemas-0.11.1.dist-info/LICENSE
yadage_schemas-0.11.1.dist-info/METADATA
yadage_schemas-0.11.1.dist-info/WHEEL
yadage_schemas-0.11.1.dist-info/entry_points.txt
yadage_schemas-0.11.1.dist-info/top_level.txt
yadage_schemas-0.11.1.dist-info/RECORD
