Metadata-Version: 2.1
Name: yadage-schemas
Version: 0.11.1
Summary: schemas for yadage and packtivity
Author: Lukas Heinrich, Matthew Feickert
Author-email: lukas.heinrich@gmail.com, matthew.feickert@cern.ch
Classifier: Development Status :: 4 - Beta
Classifier: Intended Audience :: Science/Research
Classifier: License :: OSI Approved :: MIT License
Classifier: Programming Language :: Python :: 3
Classifier: Programming Language :: Python :: 3 :: Only
Classifier: Programming Language :: Python :: 3.7
Classifier: Programming Language :: Python :: 3.8
Classifier: Programming Language :: Python :: 3.9
Classifier: Programming Language :: Python :: 3.10
Classifier: Programming Language :: Python :: 3.11
Classifier: Programming Language :: Python :: Implementation :: CPython
Classifier: Topic :: Scientific/Engineering
Classifier: Topic :: Scientific/Engineering :: Physics
Classifier: Operating System :: OS Independent
Requires-Python: >=3.7
License-File: LICENSE
Requires-Dist: jsonref
Requires-Dist: pyyaml
Requires-Dist: requests[security] >=2.9
Requires-Dist: jsonschema <=4.9.1
Requires-Dist: click
Requires-Dist: six >=1.4.0
Requires-Dist: importlib-resources >=5.10 ; python_version < "3.9"
Provides-Extra: develop
Requires-Dist: pyflakes ; extra == 'develop'
Requires-Dist: pytest >=3.2.0 ; extra == 'develop'
Requires-Dist: pytest-cov >=2.5.1 ; extra == 'develop'
Requires-Dist: python-coveralls ; extra == 'develop'
